nonebot_plugin_wearskirt/__init__.py
nonebot_plugin_wearskirt/config.py
nonebot_plugin_wearskirt/wear_skirt.py
nonebot_plugin_wearskirt-0.1.5.dist-info/LICENSE
nonebot_plugin_wearskirt-0.1.5.dist-info/METADATA
nonebot_plugin_wearskirt-0.1.5.dist-info/WHEEL
nonebot_plugin_wearskirt-0.1.5.dist-info/RECORD
