Metadata-Version: 2.1
Name: nonebot-plugin-wearskirt
Version: 0.1.5
Summary: Nonebot 赛博女装插件
License: MIT
Author: 泠风寒声
Author-email: me@lfhsheng.com
Requires-Python: >=3.8,<4.0
Classifier: License :: OSI Approved :: MIT License
Classifier: Programming Language :: Python :: 3
Classifier: Programming Language :: Python :: 3.8
Classifier: Programming Language :: Python :: 3.9
Classifier: Programming Language :: Python :: 3.10
Classifier: Programming Language :: Python :: 3.11
Requires-Dist: nonebot-plugin-localstore (>=0.5.0,<0.6.0)
Requires-Dist: nonebot2 (>=2.0.1,<3.0.0)
